unicorner_cam_streamer/__init__.py
unicorner_cam_streamer/camera_streamer.py
unicorner_cam_streamer-0.3.0.dist-info/licenses/LICENSE
unicorner_cam_streamer-0.3.0.dist-info/METADATA
unicorner_cam_streamer-0.3.0.dist-info/WHEEL
unicorner_cam_streamer-0.3.0.dist-info/top_level.txt
unicorner_cam_streamer-0.3.0.dist-info/RECORD
