Metadata-Version: 2.4
Name: unicorner-cam-streamer
Version: 0.3.0
Summary: UNICORNER Coffee’s cross-platform CameraStreamer
Author-email: Ruslan Kovalev <kovalyovruslan@gmail.com>
Requires-Python: >=3.7
License-File: LICENSE
Requires-Dist: opencv-python>=4.5
Dynamic: license-file
